tensossht/__init__.py
tensossht/conftest.py
tensossht/iterators.py
tensossht/layers/__init__.py
tensossht/layers/harmonic_transforms.py
tensossht/layers/harmonic_transforms.rst
tensossht/layers/memory_layout.py
tensossht/layers/memory_layout.rst
tensossht/layers/wigner.py
tensossht/layers/wigner.rst
tensossht/references.py
tensossht/sampling.py
tensossht/specialfunctions/__init__.py
tensossht/specialfunctions/kostelec.py
tensossht/specialfunctions/naive.py
tensossht/specialfunctions/numericalrecipes.py
tensossht/specialfunctions/risbo.py
tensossht/specialfunctions/trapani.py
tensossht/transforms/__init__.py
tensossht/transforms/coeffs_to_fmm.py
tensossht/transforms/fmm_to_gmm.py
tensossht/transforms/forward.py
tensossht/transforms/gmm_to_coeffs.py
tensossht/transforms/harmonic_transform.rst
tensossht/transforms/images_to_fmm.py
tensossht/transforms/inverse.py
tensossht/transforms/theta_extension.py
tensossht/transforms/theta_extension.rst
tensossht/transforms/transforms.py
tensossht/typing.py
tensossht-0.7.0.dist-info/LICENSE
tensossht-0.7.0.dist-info/WHEEL
tensossht-0.7.0.dist-info/METADATA
tensossht-0.7.0.dist-info/RECORD
